QForestMath/__init__.py
QForestMath/add.py
QForestMath/divide.py
QForestMath/multiply.py
QForestMath/qforest_matherror.py
QForestMath/subtract.py
QForestMath-0.0.4.dist-info/LICENSE.txt
QForestMath-0.0.4.dist-info/METADATA
QForestMath-0.0.4.dist-info/WHEEL
QForestMath-0.0.4.dist-info/top_level.txt
QForestMath-0.0.4.dist-info/RECORD
