Metadata-Version: 2.1
Name: QForestMath
Version: 0.0.4
Summary: A small math wrapper for QISkit.
Home-page: https://github.com/SashwatAnagolum/DoNew/tree/master/qforest_math
Author: Sashwat Anagolum
Author-email: sashwat.anagolum@gmail.com
License: MIT License
Platform: UNKNOWN
Classifier: Programming Language :: Python :: 3
Classifier: License :: OSI Approved :: MIT License
Classifier: Operating System :: OS Independent
Requires: q
Requires: i
Requires: s
Requires: k
Requires: i
Requires: t
